{
  "generated_at": "2026-04-03T12:29:06Z",
  "git": {
    "sha": "1a9466c102875f399f6ebf7801e1c35a5f9438b3",
    "short_sha": "1a9466c1",
    "branch": "main"
  },
  "tasks": {
    "in_progress": 2,
    "done": 22,
    "total": 24
  },
  "tasks_by_category": {
    "backend": 13,
    "narrative": 1,
    "frontend": 8,
    "assets": 3,
    "analytics": 4
  },
  "backend": {
    "domain": 143,
    "application": 56,
    "infrastructure": 62,
    "presentation": 0,
    "total": 252,
    "test_total": 8,
    "asset_generator": 50
  },
  "narrative": {
    "quests": 15,
    "npcs": 11,
    "world_events": 15,
    "conflicts": 10,
    "world": 0,
    "endings": 10,
    "player_actions": 14,
    "reviews": 0,
    "asset_specs": 63,
    "total": 76
  },
  "ci": {
    "status": "in_progress",
    "conclusion": "pending",
    "total_runs": 2,
    "failed_checks": 0,
    "success_checks": 0
  }
}
