<?xml version="1.0" encoding="UTF-8"?>
<player-actions>

    <action id="GO_TO_WORK" code="GO_TO_WORK" time-cost="8">
        <label>Пойти на работу</label>
        <description>Работать над проектом</description>
        <result-text>Татьяна поработала {timeCost} часов. Устала, но заработала деньги.</result-text>
        <time-cost-skill skill="efficiency" reduction-per-level="0.02" min-cost="6"/>
        <stats energy="-30" health="0" stress="20" mood="-5" money="55" self-esteem="0"/>
        <relationships>
            <change target="HUSBAND" delta="-5"/>
            <change target="FATHER" delta="-2"/>
        </relationships>
        <pet-mood/>
        <flags rested="false" worked="true" interacted-npcs="" reset-household-days="false"/>
        <skill-gains>
            <skill name="efficiency" xp="2"/>
        </skill-gains>
        <job-effects satisfaction="2" burnout-risk="0"/>
    </action>

    <action id="VISIT_FATHER" code="VISIT_FATHER" time-cost="4">
        <label>Поехать к отцу</label>
        <description>Навестить отца</description>
        <result-text>Татьяна навестила отца. Он рад визиту.</result-text>
        <stats energy="-15" health="0" stress="0" mood="10" money="0" self-esteem="0"/>
        <relationships>
            <change target="FATHER" delta="15"/>
        </relationships>
        <pet-mood/>
        <flags rested="false" worked="false" interacted-npcs="FATHER" reset-household-days="false"/>
        <skill-gains>
            <skill name="empathy" xp="2"/>
            <skill name="communication" xp="1"/>
        </skill-gains>
        <extra-relationship-effects>
            <effect target="FATHER" closeness="0" trust="5" stability="0" romance="0"/>
        </extra-relationship-effects>
    </action>

    <action id="DATE_WITH_HUSBAND" code="DATE_WITH_HUSBAND" time-cost="3">
        <label>Свидание с мужем</label>
        <description>Романтический вечер</description>
        <result-text>Татьяна провела романтический вечер с мужем.</result-text>
        <stats energy="-10" health="0" stress="-10" mood="20" money="0" self-esteem="0"/>
        <relationships>
            <change target="HUSBAND" delta="10"/>
        </relationships>
        <pet-mood/>
        <flags rested="false" worked="false" interacted-npcs="HUSBAND" reset-household-days="false"/>
        <skill-gains>
            <skill name="charisma" xp="2"/>
            <skill name="empathy" xp="1"/>
        </skill-gains>
        <extra-relationship-effects>
            <effect target="HUSBAND" closeness="0" trust="5" stability="0" romance="15"/>
        </extra-relationship-effects>
    </action>

    <action id="PLAY_WITH_CAT" code="PLAY_WITH_CAT" time-cost="1">
        <label>Поиграть с Гарфилдом</label>
        <description>Время с котом</description>
        <result-text>Татьяна поиграла с Барсиком. Кот доволен.</result-text>
        <stats energy="-5" health="0" stress="-5" mood="10" money="0" self-esteem="0"/>
        <relationships/>
        <pet-mood>
            <change target="BARSIK" delta="20"/>
        </pet-mood>
        <flags rested="false" worked="false" interacted-npcs="" reset-household-days="false"/>
        <skill-gains>
            <skill name="empathy" xp="1"/>
        </skill-gains>
    </action>

    <action id="WALK_DOG" code="WALK_DOG" time-cost="2">
        <label>Погулять с Сэмом</label>
        <description>Прогулка с собакой</description>
        <result-text>Татьяна погуляла с Сэмом. Свежий воздух пошёл на пользу.</result-text>
        <time-cost-skill skill="dog_care" reduction-per-level="0.02" min-cost="1"/>
        <stats energy="-10" health="5" stress="-10" mood="10" money="0" self-esteem="0"/>
        <relationships/>
        <pet-mood>
            <change target="SAM" delta="25"/>
        </pet-mood>
        <flags rested="false" worked="false" interacted-npcs="" reset-household-days="false"/>
        <skill-gains>
            <skill name="dog_care" xp="2"/>
        </skill-gains>
    </action>

    <action id="SELF_CARE" code="SELF_CARE" time-cost="2">
        <label>Заняться собой</label>
        <description>Время для себя</description>
        <result-text>Татьяна уделила время себе. Стресс отступил.</result-text>
        <stats energy="-10" health="0" stress="-15" mood="15" money="0" self-esteem="10"/>
        <relationships/>
        <pet-mood/>
        <flags rested="false" worked="false" interacted-npcs="" reset-household-days="false"/>
        <skill-gains>
            <skill name="assertiveness" xp="2"/>
            <skill name="communication" xp="1"/>
        </skill-gains>
        <job-effects satisfaction="0" burnout-risk="-3"/>
    </action>

    <action id="REST_AT_HOME" code="REST_AT_HOME" time-cost="3">
        <label>Отдохнуть дома</label>
        <description>Отдых и восстановление</description>
        <result-text>Татьяна отдохнула дома. Силы восстановлены.</result-text>
        <stats energy="40" health="0" stress="-20" mood="10" money="0" self-esteem="0"/>
        <relationships/>
        <pet-mood/>
        <flags rested="true" worked="false" interacted-npcs="" reset-household-days="false"/>
        <skill-gains>
            <skill name="humor" xp="1"/>
        </skill-gains>
    </action>

    <action id="HOUSEHOLD" code="HOUSEHOLD" time-cost="2">
        <label>Домашние дела</label>
        <description>Уборка, готовка, уют в доме</description>
        <result-text>Домашние дела сделаны. Муж ценит уют, но вы немного устали.</result-text>
        <stats energy="-15" health="0" stress="0" mood="-5" money="0" self-esteem="0"/>
        <relationships>
            <change target="HUSBAND" delta="5"/>
        </relationships>
        <pet-mood/>
        <flags rested="false" worked="false" interacted-npcs="HUSBAND" reset-household-days="true"/>
        <skill-gains>
            <skill name="cooking" xp="2"/>
        </skill-gains>
    </action>

</player-actions>
